{
  "viaje": {
    "nombre": "Europa 2027",
    "familias": ["Barrera", "Nader", "Ahmad"],
    "total_personas": 14,
    "fecha_ida": "2027-01-28",
    "fecha_vuelta": "2027-02-15"
  },

  "personas": {
    "Barrera": [
      { "nombre": "Alvaro Abel Barrera Yane", "rol": "Adulto", "pasaporte": "ok" },
      { "nombre": "Maria Veronica Posleman", "rol": "Adulto", "pasaporte": "ok" },
      { "nombre": "Lucas Barrera Posleman", "rol": "Menor", "pasaporte": "pending" },
      { "nombre": "Camila Barrera Posleman", "rol": "Menor", "pasaporte": "ok" },
      { "nombre": "Macarena Barrera Posleman", "rol": "Menor", "pasaporte": "ok" }
    ],
    "Nader": [
      { "nombre": "Francisco Jose Nader Zelaya", "rol": "Adulto", "pasaporte": "ok" },
      { "nombre": "Maria Gabriela Rolandi", "rol": "Adulto", "pasaporte": "ok" },
      { "nombre": "Juan Jose Nader", "rol": "Menor", "pasaporte": "ok" },
      { "nombre": "Tomas Nader", "rol": "Menor", "pasaporte": "pending" },
      { "nombre": "Santiago Nader", "rol": "Menor", "pasaporte": "ok" }
    ],
    "Ahmad": [
      { "nombre": "Miguel Angel Ahmad", "rol": "Adulto", "pasaporte": "ok" },
      { "nombre": "Lisa Maria Beti", "rol": "Adulto", "pasaporte": "ok" },
      { "nombre": "Maria Sofia Ahmad", "rol": "Menor", "pasaporte": "ok" },
      { "nombre": "Maria Julieta Ahmad", "rol": "Menor", "pasaporte": "pending" }
    ]
  },

  "vuelos": [
    { "id": "SAO-LON", "tipo": "vuelo", "origen": "Sao Paulo (GRU)", "destino": "Londres (LHR)", "fecha": "2027-01-28", "aerolinea": "British Airways", "numero": "BA0246", "salida": "16:25", "llegada": "06:45+1", "confirmado": false, "pnr": { "Barrera": null, "Nader": "YV77JC", "Ahmad": null } },
    { "id": "LON-PAR", "tipo": "tren", "origen": "Londres (St Pancras)", "destino": "Paris (Gare du Nord)", "fecha": "2027-02-02", "empresa": "Eurostar", "numero": null, "salida": "12:30", "llegada": "16:00", "confirmado": false, "pnr": { "Barrera": null, "Nader": null, "Ahmad": null } },
    { "id": "PAR-BRU", "tipo": "tren", "origen": "Paris (Gare du Nord)", "destino": "Bruselas (Brussels-Midi)", "fecha": "2027-02-06", "empresa": "Eurorail", "numero": null, "salida": "08:55", "llegada": "10:16", "confirmado": false, "pnr": { "Barrera": null, "Nader": null, "Ahmad": null } },
    { "id": "BRU-ROM", "tipo": "vuelo", "origen": "Bruselas (BRU)", "destino": "Roma (FCO)", "fecha": "2027-02-07", "aerolinea": null, "numero": null, "salida": null, "llegada": null, "confirmado": false, "pnr": { "Barrera": null, "Nader": null, "Ahmad": null } },
    { "id": "ROM-MAD", "tipo": "vuelo", "origen": "Roma (FCO)", "destino": "Madrid (MAD)", "fecha": "2027-02-11", "aerolinea": "Iberia", "numero": "IB0648", "salida": "12:00", "llegada": "14:35", "confirmado": true, "pnr": { "Barrera": null, "Nader": "J5SQ1", "Ahmad": null } },
    { "id": "MAD-EZE", "tipo": "vuelo", "origen": "Madrid (MAD)", "destino": "Buenos Aires (EZE)", "fecha": "2027-02-15", "aerolinea": "Iberia", "numero": "IB0101", "salida": "01:05", "llegada": "08:45+1", "confirmado": true, "pnr": { "Barrera": null, "Nader": "NZB0P", "Ahmad": null } }
  ],

  "hoteles": [
    {
      "ciudad": "Londres",
      "fechas": { "checkin": "2027-01-29", "checkout": "2027-02-02" },
      "nombre": "Urban Chic - Shaftesbury",
      "direccion": "Shaftesbury Ave, London W1D 5EB",
      "maps_url": "https://maps.google.com/?q=Shaftesbury+Ave+London+W1D+5EB",
      "como_llegar_desde_aeropuerto": "Desde LHR tomar Underground Piccadilly Line hasta Piccadilly Circus o Leicester Square. NO tomar la Elizabeth Line. Marcar la tarjeta al entrar Y al salir.",
      "reservas": {
        "Barrera": { "confirmacion": "73412725729257", "precio": "USD 1421.53", "habitacion": null, "obs": null },
        "Nader":   { "confirmacion": "73412569141433", "precio": "USD 1599.21", "habitacion": null, "obs": null },
        "Ahmad":   { "confirmacion": "73412571168271", "precio": "USD 1163.17", "habitacion": null, "obs": null }
      }
    },
    {
      "ciudad": "Paris",
      "fechas": { "checkin": "2027-02-02", "checkout": "2027-02-06" },
      "nota": "Alojamiento separado por familia",
      "como_llegar_desde_aeropuerto": "Desde CDG tomar RER B hasta centro. Marcar al entrar Y al salir.",
      "reservas": {
        "Barrera": { "nombre": null, "direccion": null, "confirmacion": null, "precio": null, "maps_url": null, "obs": "Por confirmar" },
        "Nader":   { "nombre": "Sweett - Pavillon Opera", "direccion": "7 Rue Monsigny, 75002 Paris", "confirmacion": "996116490", "precio": "EUR 1265.56", "maps_url": "https://maps.google.com/?q=7+Rue+Monsigny+Paris+75002", "obs": null },
        "Ahmad":   { "nombre": "Sublime Apartment Louvre Concorde Museum", "direccion": "Rue de l'Oratoire 6, 75001 Paris", "confirmacion": "73405723297848", "precio": "EUR 944.33", "maps_url": "https://maps.google.com/?q=Rue+de+l+Oratoire+6+Paris+75001", "obs": null }
      }
    },
    {
      "ciudad": "Bruselas",
      "fechas": { "checkin": "2027-02-06", "checkout": "2027-02-07" },
      "nombre": "Hotel NH Brussels Carrefour de l'Europe",
      "direccion": "Rue du Marché aux Herbes 110, 1000 Bruxelles, Bélgica",
      "maps_url": "https://maps.google.com/?q=Rue+du+Marche+aux+Herbes+110+1000+Bruxelles",
      "como_llegar_desde_aeropuerto": "Desde BRU tomar tren directo a Bruxelles-Central. Marcar siempre aunque no haya control visible.",
      "habitaciones": {
        "dobles":      { "cantidad": 3, "confirmacion": "73474107361490", "asignacion": "1 doble Ahmad (2) + 1 doble Nader (2) + 1 doble Barrera (2)" },
        "cuadruples":  { "cantidad": 2, "confirmacion": "73474100905258", "asignacion": "Cuadruple A: 2 Ahmad + 2 Barrera | Cuadruple B: 3 Nader + 1 Barrera" }
      },
      "fecha_pago": "2027-01-30",
      "metodo_pago": "Tarjeta Galicia Gaby",
      "reservas": {
        "Barrera": { "confirmacion": "73474107361490 / 73474100905258", "precio": "EUR 423.00", "habitacion": "1 doble (2 Barrera) + 2 Barrera en Cuadruple A + 1 Barrera en Cuadruple B", "obs": "5 pax repartidos entre 3 habitaciones" },
        "Nader":   { "confirmacion": "73474107361490 / 73474100905258", "precio": "EUR 423.00", "habitacion": "1 doble (2 Nader) + Cuadruple B (3 Nader)", "obs": "5 pax repartidos entre 2 habitaciones" },
        "Ahmad":   { "confirmacion": "73474107361490 / 73474100905258", "precio": "EUR 351.41", "habitacion": "1 doble (2 Ahmad) + Cuadruple A (2 Ahmad)", "obs": "4 pax repartidos entre 2 habitaciones" }
      }
    },
    {
      "ciudad": "Roma",
      "fechas": { "checkin": "2027-02-07", "checkout": "2027-02-11" },
      "nombre": "Hotel Scalinata di Spagna",
      "direccion": "Piazza Trinita dei Monti 17, 00187 Roma",
      "maps_url": "https://maps.google.com/?q=Piazza+Trinita+dei+Monti+17+Roma",
      "como_llegar_desde_aeropuerto": "Desde FCO: traslado privado con Monza/Downtown Travel. Alternativa: Leonardo Express hasta Roma Termini.",
      "confirmacion_general": "070227",
      "reservas": {
        "Barrera": { "confirmacion": "070227", "precio": "EUR 1340.00", "habitacion": "Family Suite con balcone 5 pax", "obs": "Sin asignacion individual aun" },
        "Nader":   { "confirmacion": "070227", "precio": "EUR 1090.00", "habitacion": "Appartamento Grand Tour 5 pax", "obs": null },
        "Ahmad":   { "confirmacion": "070227", "precio": "EUR 840.00",  "habitacion": "Camera Quadrupla 4 pax", "obs": null }
      }
    },
    {
      "ciudad": "Madrid",
      "fechas": { "checkin": "2027-02-11", "checkout": "2027-02-15" },
      "nombre": "Carretas Apartments Madrid",
      "direccion": "Carretas 8, 28012 Madrid",
      "maps_url": "https://maps.google.com/?q=Carretas+8+Madrid+28012",
      "como_llegar_desde_aeropuerto": "Metro Linea 8 (rosa) hasta Nuevos Ministerios + transbordo. O taxi directo ~30 min.",
      "reservas": {
        "Barrera": { "confirmacion": "73408485414202", "precio": "EUR 585.00", "habitacion": "Apt 301", "obs": null },
        "Nader":   { "confirmacion": "73406500259432", "precio": "EUR 585.00", "habitacion": "Apt 101", "obs": null },
        "Ahmad":   { "confirmacion": "73408794452079", "precio": "EUR 585.00", "habitacion": "Apt 201", "obs": null }
      }
    }
  ],

  "pendientes": [
    { "item": "PNR Barrera y Ahmad — BA0246 SAO-LON",               "categoria": "transportes",    "familia": "Barrera/Ahmad", "prioridad": "alta",  "hecho": false },
    { "item": "PNR Barrera y Ahmad — IB0648 ROM-MAD",               "categoria": "transportes",    "familia": "Barrera/Ahmad", "prioridad": "alta",  "hecho": false },
    { "item": "PNR todas las familias — IB0101 MAD-EZE",            "categoria": "transportes",    "familia": "Todas",         "prioridad": "alta",  "hecho": false },
    { "item": "Reserva tren Eurostar LON-PAR (tickets por familia)", "categoria": "transportes",    "familia": "Todas",         "prioridad": "alta",  "hecho": false },
    { "item": "Reserva tren Thalys PAR-BRU",                        "categoria": "transportes",    "familia": "Todas",         "prioridad": "alta",  "hecho": false },
    { "item": "Vuelo BRU-ROM (aerolinea y numero)",                  "categoria": "transportes",    "familia": "Todas",         "prioridad": "alta",  "hecho": false },
    { "item": "Alojamiento Paris — Barrera",                        "categoria": "transportes",    "familia": "Barrera",       "prioridad": "alta",  "hecho": false },
    { "item": "Asignacion habitaciones Roma entre familias",         "categoria": "logistica",      "familia": "Todas",         "prioridad": "baja",  "hecho": false },
    { "item": "Pasaporte Lucas Barrera Posleman",                    "categoria": "documentacion",  "familia": "Barrera",       "prioridad": "alta",  "hecho": false },
    { "item": "Pasaporte Tomas Nader",                               "categoria": "documentacion",  "familia": "Nader",         "prioridad": "alta",  "hecho": false },
    { "item": "Pasaporte Maria Julieta Ahmad",                       "categoria": "documentacion",  "familia": "Ahmad",         "prioridad": "alta",  "hecho": false },
    { "item": "Boarding passes subir a la app",                      "categoria": "documentacion",  "familia": "Todas",         "prioridad": "media", "hecho": false },
    { "item": "Boton como llegar con Google Maps",                   "categoria": "logistica",      "familia": null,            "prioridad": "baja",  "hecho": true  }
  ],

  "drive": {
    "raiz_id": "1MxbTztDMdw7eeEMvyF9FylGm-QVnVt86"
  },

  "meta": {
    "version": "1.5",
    "ultima_actualizacion": "2026-06-25",
    "notas": "v1.5: Tren Eurorail Paris-Bruselas con horario (sale 08:55 Gare du Nord, llega 10:16 Brussels-Midi)."
  }
}
